ToMiddleChinese/ToMiddleChinese.py
ToMiddleChinese/__init__.py
ToMiddleChinese/utils.py
ToMiddleChinese/version.py
ToMiddleChinese/dict/HKVariantsRev.txt
ToMiddleChinese/dict/HKVariantsRevPhrases.txt
ToMiddleChinese/dict/dict.big.txt
ToMiddleChinese/dict/hk2t.json
ToMiddleChinese/dict/kyonh.dict.yaml
ToMiddleChinese/dict/pos.dict.yaml
ToMiddleChinese/dict/tupa.dict.yaml
ToMiddleChinese/dict/unt.dict.yaml
ToMiddleChinese-0.2.2.dist-info/LICENSE
ToMiddleChinese-0.2.2.dist-info/METADATA
ToMiddleChinese-0.2.2.dist-info/WHEEL
ToMiddleChinese-0.2.2.dist-info/top_level.txt
ToMiddleChinese-0.2.2.dist-info/RECORD
