Metadata-Version: 2.1
Name: ToMiddleChinese
Version: 0.2.2
Summary: 中古漢語自動標註工具 Middle Chinese Pronunciation Automatic Labeling Tool
Home-page: https://github.com/nk2028/ToMiddleChinese
Author: Ngiox Khyen 2028 Project
Author-email: support@mail.nk2028.shn.hk
Project-URL: Bug Reports, https://github.com/nk2028/ToMiddleChinese/issues
Project-URL: Source, https://github.com/nk2028/ToMiddleChinese
Keywords: chinese middle-chinese linguistics nlp natural-language-processing
Classifier: Development Status :: 4 - Beta
Classifier: Intended Audience :: Developers
Classifier: Topic :: Software Development :: Libraries :: Python Modules
Classifier: Topic :: Text Processing :: Linguistic
Classifier: Natural Language :: Chinese (Simplified)
Classifier: Natural Language :: Chinese (Traditional)
Classifier: License :: CC0 1.0 Universal (CC0 1.0) Public Domain Dedication
Classifier: Programming Language :: Python :: 3
Classifier: Programming Language :: Python :: 3.5
Classifier: Programming Language :: Python :: 3.6
Classifier: Programming Language :: Python :: 3.7
Classifier: Programming Language :: Python :: 3.8
Classifier: Programming Language :: Python :: 3.9
Classifier: Programming Language :: Python :: 3.10
Classifier: Programming Language :: Python :: 3.11
Requires-Python: >=3.5, <4
License-File: LICENSE
Requires-Dist: pygtrie
Requires-Dist: opencc (!=1.1.1)
Requires-Dist: jieba
